idem_virtualbox/conf.py
idem_virtualbox/version.py
idem_virtualbox/exec/virtualbox.py
idem_virtualbox/states/virtualbox.py
idem_virtualbox-1.dist-info/METADATA
idem_virtualbox-1.dist-info/WHEEL
idem_virtualbox-1.dist-info/top_level.txt
idem_virtualbox-1.dist-info/RECORD
