Metadata-Version: 2.1
Name: idem-virtualbox
Version: 1
Summary: UNKNOWN
Home-page: UNKNOWN
Author: 
Author-email: 
License: UNKNOWN
Platform: UNKNOWN
Classifier: Operating System :: OS Independent
Classifier: Programming Language :: Python
Classifier: Programming Language :: Python :: 3.6
Classifier: Programming Language :: Python :: 3.7
Classifier: Programming Language :: Python :: 3.8
Classifier: Development Status :: 5 - Production/Stable
Requires-Python: >=3.6
Requires-Dist: idem (>=7)
Requires-Dist: pop (>=13)
Requires-Dist: pop-config (>=6)
Requires-Dist: virtualbox (>=2.0.0)
Requires-Dist: idem-bsd ; "BSD" in sys_platform
Requires-Dist: idem-solaris ; "sunos" in sys_platform
Requires-Dist: idem-darwin ; sys_platform == "darwin"
Requires-Dist: idem-linux ; sys_platform == "linux"
Requires-Dist: idem-windows ; sys_platform == "win32"
